sphinx_parser/__init__.py
sphinx_parser/_version.py
sphinx_parser/ase.py
sphinx_parser/input.py
sphinx_parser/jobs.py
sphinx_parser/output.py
sphinx_parser/potential.py
sphinx_parser/toolkit.py
sphinx_parser/src/generator.py
sphinx_parser-0.1.5.dist-info/licenses/LICENSE
sphinx_parser-0.1.5.dist-info/METADATA
sphinx_parser-0.1.5.dist-info/WHEEL
sphinx_parser-0.1.5.dist-info/top_level.txt
sphinx_parser-0.1.5.dist-info/RECORD
