Metadata-Version: 2.4
Name: sphinx_parser
Version: 0.1.5
Summary: sphinx_parser - Your pyiron-like module.
Author-email: Lorem Ipsum <lorem@ipsum.com>
License: BSD 3-Clause License
Project-URL: Homepage, https://pyiron.org/
Project-URL: Documentation, https://sphinx_parser.readthedocs.io
Project-URL: Repository, https://github.com/pyiron/sphinx_parser
Keywords: pyiron
Classifier: Development Status :: 3 - Alpha
Classifier: Topic :: Scientific/Engineering
Classifier: License :: OSI Approved :: BSD License
Classifier: Intended Audience :: Science/Research
Classifier: Operating System :: OS Independent
Classifier: Programming Language :: Python :: 3.11
Classifier: Programming Language :: Python :: 3.12
Classifier: Programming Language :: Python :: 3.13
Classifier: Programming Language :: Python :: 3.14
Requires-Python: <3.15,>=3.9
License-File: LICENSE
Requires-Dist: numpy<2.4.0,>=1.26.4
Requires-Dist: ase<3.27.0,>=3.23.0
Requires-Dist: h5py<3.16.0,>=3.6.0
Requires-Dist: semantikon<=0.0.26,>=0.0.17
Requires-Dist: pint<=0.25.2,>=0.23
Dynamic: license-file
